hangfirekiller/__init__.py
hangfirekiller/main.py
hangfirekiller/models.py
hangfirekiller-0.1.0.dist-info/METADATA
hangfirekiller-0.1.0.dist-info/WHEEL
hangfirekiller-0.1.0.dist-info/entry_points.txt
hangfirekiller-0.1.0.dist-info/RECORD
